az_index_maker/__init__.py
az_index_maker/az_index_maker.py
az_index_maker-0.1.0.dist-info/METADATA
az_index_maker-0.1.0.dist-info/WHEEL
az_index_maker-0.1.0.dist-info/license
az_index_maker-0.1.0.dist-info/top_level.txt
az_index_maker-0.1.0.dist-info/RECORD
